{
  "safetyTips": "Wearing face-mask and sanitising before and after each delivery. Orders are delivered in paper carrier bags that have handles to ensure minimal surface contact. Delivery is left, doorbell rang or door knocked, then I step back to the pavement to wait for customer to acknowledge me. ",
  "name": "Redhill Confetti",
  "phone": "07798551120",
  "address": "Keats Avenue, Redhill RH1 1AG",
  "cover": "https://res.cloudinary.com/reigate-delivers/image/upload/c_limit,f_auto,q_80,w_500/v1588146839/use-redhill-confetti_csacst.jpg",
  "tags": [
    "Gifts",
    "Homewares"
  ],
  "website": "https://www.etsy.com/uk/shop/Redhillconfetti",
  "deliveryHours": [
    "Tuesday 15:00 - 18:00",
    "Friday 15:00 - 18:00"
  ],
  "email": "redhillconfetti@gmail.com",
  "description": "Handmade crafts and make-at-home kits to entertain kids and adults alike."
}